truffle/__init__.py
truffle/app.py
truffle/dummy.py
truffle/filetools.py
truffle/global_constants.py
truffle/indextools.py
truffle/indextools_test.py
truffle/text_index.py
truffle/frontend/.DS_Store
truffle/frontend/__init__.py
truffle/frontend/static/__init__.py
truffle/frontend/static/css/__init__.py
truffle/frontend/static/js/__init__.py
truffle/frontend/static/js/lib/__init__.py
truffle/frontend/templates/__init__.py
truffle/indexdir/__init__.py
truffle/parsers/__init__.py
truffle/parsers/pyparser.py
truffle/parsers/pywalker.py
truffle/parsers/pywalker_test.py
truffle-0.1.dev0.dist-info/DESCRIPTION.rst
truffle-0.1.dev0.dist-info/METADATA
truffle-0.1.dev0.dist-info/RECORD
truffle-0.1.dev0.dist-info/WHEEL
truffle-0.1.dev0.dist-info/entry_points.txt
truffle-0.1.dev0.dist-info/metadata.json
truffle-0.1.dev0.dist-info/top_level.txt
